[
  {
    "type": "room",
    "position": {
      "x": 0,
      "y": 0
    },
    "dimensions": {
      "width": 1,
      "height": 1
    },
    "data": {
      "stars": 1
    }
  },
  {
    "type": "room",
    "position": {
      "x": 0,
      "y": 1
    },
    "dimensions": {
      "width": 1,
      "height": 1
    },
    "data": {
      "stars": 1
    }
  },
  {
    "type": "room",
    "position": {
      "x": 0,
      "y": 2
    },
    "dimensions": {
      "width": 1,
      "height": 1
    },
    "data": {
      "stars": 1
    }
  },
  {
    "type": "room",
    "position": {
      "x": 1,
      "y": 1
    },
    "dimensions": {
      "width": 1,
      "height": 1
    },
    "data": {
      "stars": 1
    }
  },
  {
    "type": "room",
    "position": {
      "x": 1,
      "y": 2
    },
    "dimensions": {
      "width": 1,
      "height": 1
    },
    "data": {
      "stars": 1
    }
  },
  {
    "type": "room",
    "position": {
      "x": 2,
      "y": 3
    },
    "dimensions": {
      "width": 2,
      "height": 2
    },
    "data": {
      "stars": 2
    }
  },
  {
    "type": "movie",
    "position": {
      "x": 5,
      "y": 5
    },
    "dimensions": {
      "width": 3,
      "height": 3
    },
    "data": {}
  },
  {
    "type": "diner",
    "position": {
      "x": 1,
      "y": 5
    },
    "dimensions": {
      "width": 2,
      "height": 1
    },
    "data": {
      "max": 2
    }
  },
  {
    "type": "fitness",
    "position": {
      "x": 9,
      "y": 9
    },
    "dimensions": {
      "width": 6,
      "height": 5
    },
    "data": {
      "max": 200
    }
  }
]